my_component/__init__.py
my_component/frontend/build/asset-manifest.json
my_component/frontend/build/bootstrap.min.css
my_component/frontend/build/index.html
my_component/frontend/build/static/js/main.602c43be.js
my_component/frontend/build/static/js/main.602c43be.js.LICENSE.txt
my_component/frontend/build/static/js/main.602c43be.js.map
geoflow_capability_search-0.0.18.dist-info/LICENSE
geoflow_capability_search-0.0.18.dist-info/METADATA
geoflow_capability_search-0.0.18.dist-info/WHEEL
geoflow_capability_search-0.0.18.dist-info/top_level.txt
geoflow_capability_search-0.0.18.dist-info/RECORD
