Metadata-Version: 2.1
Name: geoflow-capability-search
Version: 0.0.18
Summary: Streamlit component that allows you to deal with capability search for geoflow app
Home-page: 
Author: Sergei Ozerov
Author-email: ozerovsa@gmail.com
Requires-Python: >=3.7
License-File: LICENSE
Requires-Dist: streamlit >=0.63
